{"url": "https://academicpositions.com/ad/umea-university/2021/up-to-five-tenure-track-positions-as-assistant-professor/173355", "title": "Up to five tenure-track positions as Assistant professor", "publish_date": "2021-12-22", "deadline": "2022-02-15", "location": "Biblioteksgr\u00c3\u00a4nd 6 Ume\u00c3\u00a5, Sweden", "city": "N/A", "country": "Sweden", "position": "Assistant Professor", "field": "Applied Mathematics, Architecture, Industrial Design, Science Education, Technology Education,", "salary": "N/A", "max_working_hours": "N/A", "employer": "Ume\u00c3\u00a5 University", "job_description": "Ume\u00c3\u00a5 University, Faculty of Science and TechnologyWelcome to apply to become one of our new Assistant Professors! With this faculty joint venture, with a six-year appointment we want to give junior researchers the opportunity to develop a long-term research activity and to qualify for promotion to an Associate Professorship (Senior Lecturer). Welcome with your application!Description of the employmentThe persons we seek will conduct research and contribute to the continued development of the research environment in their respective field. Included in the work tasks are developing pedagogical merits that include teaching in undergraduate and graduate levels, as well as supervision of PhD students and postdocs. The person employed is expected to actively seek external funding for his or her research activities.Employment is limited to 6 years, which consists of 75% own research and 25% teaching&nbsp;or other meriting tasks. The position is a \u00e2\u0080\u009ctenure-track\u00e2\u0080\u009d, which makes it possible to develop and establish a long-term research program. An Assistant Professor has the right, upon request, to be considered for promotion to Associate Professor/ Senior Lecturer.Qualification RequirementsA person qualified for appointment as an Assistant professor is a person who has been awarded a PhD or has the corresponding research expertise. Primary consideration should be given to a person who has been awarded a PhD or achieved the equivalent expertise within five years prior to the deadline for application for employment as an Assistant professor. However, a person who has been awarded a PhD or achieved the equivalent expertise at an earlier date may also be considered if there are exceptional circumstances. Exceptional circumstances are sick leave, parental leave or other similar circumstances, according to chapter 4, section 4 of the Higher Education Ordinance.The PhD or corresponding research expertise must be in a field of relevance for the Faculty.The position requires a good knowledge of English, both spoken and written.Assessment criteriaThe assessment criteria for appointment as an Assistant professor shall be the degree of the expertise required as a qualification for employment. In addition, the degree of educational expertise, as well as administrative and other competences of importance, shall be taken into account with regard to the subject content of the employment and the duties to be included in the employment.Scientific expertiseScientific expertise shall be demonstrated through independent scientific productivity. The criteria for assessment are:Breadth and depth of research \u00e2\u0080\u0093 quality and extentOriginality in researchProductivityContributions to the international research communityCommissions of trust within the research communityAbility to competitively obtain research fundingCollaboration with the surrounding communityThe scientific expertise shall be in the fields of natural science, technology, design, architecture or science and mathematics education.Primary weight in the evaluation of candidates is placed on the degree of scientific expertise assessed from scientific work published in internationally recognized academic journals and proceedings of academic conferences that apply a peer-review system. Particular emphasis shall be placed on the quality of the publications where the applicant is the first/lead or last/senior author.Thereafter, the description of the intended research plan to be conducted within the employment shall be given substantial weight in the selection of candidates.&nbsp;Applicants with a research plan that is linked to and / or complements the department's research activities are given priority.International research experience and a postdoctoral stay at a university other than the one at which the applicant received their PhD degree are very meritorious.The documented ability to competitively obtain research funding, especially from more competitive and highly recognized funding bodies, is a merit.The demonstrated ability to independently and flexibly operate, communicate and collaborate inside and outside the academic environment is advantageous.Furthermore, the ability to independently organize, and manage projects will be considered.Pedagogical expertiseThe criteria for evaluation of pedagogical expertise are:ability to plan, implement and evaluate teaching and an ability to supervise and examine students at every level of educationability to vary teaching methods and examination forms in relation to anticipated study results and the nature of the subjectexperience of collaboration with the surrounding society in planning and implementation of educationparticipation in the development of learning environments, teaching aids and study resourcesa reflective approach to student learning and one\u00e2\u0080\u0099s own role as a teacherPedagogical expertise can be attained through education in university pedagogy, other education of relevance for teaching at a university level or documented and proven experience teaching at the university level.Candidates who do not speak Swedish at the time of appointment are expected to learn Swedish within three years from the start of the appointment.Other assessment criteriaA general basis for assessment for all teaching categories is both good cooperative skills and the expertise and suitability in general required to complete the work duties satisfactorily.The criteria for evaluation of administrative expertise are:Experiences of supervision (students, postgraduate students, postdoc)Participation in working groups or committees (department, faculty or university level)Experiences of collaboration outside the academyExperience of organizing research and educational activitiesAssessment criteria and their weightIn the selection of candidates, the degree of research expertise shall be decisive. In addition, the degree of educational expertise, as well as administrative and other competences of importance, shall be taken into account with regard to the subject content of the employment and the duties to be included in the employment.Important informationPrimary consideration for these positions is given to those applicants who have fulfilled all the requirements for a doctoral degree, such as mandatory courses, oral defense and an approved doctoral thesis after 15 February 2017 at the earliest. For applicants with Swedish doctoral degrees, the award date (date of completed studies) listed in Ladok applies (February 15, 2017 at the earliest). If you claim to have deductible time, the motivation, dates and extent must be clearly specified in the application. Applicants with older degrees will only be considered if there are not enough qualified applicants within the five-year period.We expect to receive many applications. It is therefore of the utmost importance that the application follows instructions and is complete. The application shall be submitted no later than 23.59 Swedish time (CET) on February 15, 2022, to be considered.ApplicationPlease follow the instructions carefully. The applications will be reviewed by an international panel of reviewers. For that reason, all the submitted documents should be written in EnglishPersonal letter. Please indicate here at which department that you see the position being placed at and motivate your choice.Application template (link)Documents proving the claimed deductible timeCopies of relevant degree certificatesCopies of relevant publicationsCopies of relevant pedagogical workRead more about the faculty here.Read about the research conducted at our departments here.Your application should be submitted through Ume\u00c3\u00a5 University's digital recruitment system Varbi on 2022-02-15 at the latest.Applying for promotion to Associate professorAs assistant professor, upon request, can be promoted to Associate professor if he or she meets the requirements for employment as an Associate professor and upon review is determined to meet the qualifications for such employment according to the evaluation criteria that shall be applied for promotion to Associate professor. This promotion entails a permanent position as Associate professor.Prior to the employment of an Assistant professor, the criteria for promotion shall be established. The criteria for promotion are established within the employment profile by the dean and are given below under the heading of \u00e2\u0080\u0098Promotion criteria\u00e2\u0080\u0099.The application for promotion shall be submitted six months before the fixed-term appointment ends. If an Assistant professor after evaluation is not promoted, the fixed-term appointment ends.Established criteria for promotion can be found in the employment profile decided by the dean of the Faculty of Science and Technology on December 20, 2021 (pdf).Ume\u00c3\u00a5 University&nbsp;is one of Sweden\u00e2\u0080\u0099s largest institutions of higher education with over 35,000 students and 4,200 faculty and staff. We are characterised by world-leading research in several scientific fields and a multitude of educations ranked highly in international comparison. Ume\u00c3\u00a5 University is also the site of the pioneering discovery of the CRISPR-Cas9 genetic scissors - a revolution in genetic engineering that has been awarded the Nobel Prize in Chemistry.At Ume\u00c3\u00a5 University, everything is nearby. Our cohesive campus environment makes it easy to meet, collaborate and exchange knowledge, which promotes a dynamic and open culture where we rejoice in each other's successes.Are you interested in knowing more about Ume\u00c3\u00a5 University as a workplace read more at: Work with us. As an employee at Ume\u00c3\u00a5 University, you're offered a wide variety of benefits that promote a good work-life balance, read more about benefits here.Ume\u00c3\u00a5 University wants to offer an equal environment where open dialogue between people with different backgrounds and perspectives lay the foundation for learning, creativity and development. We welcome people with different backgrounds and experiences to apply for the current employment.We kindly decline offers of recruitment and advertising help.Type of employment Temporary position longer than 6 months&nbsp;Contract type Full time&nbsp;First day of employment Upon agreement&nbsp;Salary Monthly salary&nbsp;Number of positions 1&nbsp;Working hours 100 %&nbsp;City Ume\u00c3\u00a5&nbsp;County V\u00c3\u00a4sterbottens l\u00c3\u00a4n&nbsp;Country Sweden&nbsp;Reference number AN 2.2.1-1879-21&nbsp;ContactRichard Bindler, professor, richard.bindler@umu.seUnion representativeSACO, +46 90-786 53 65SEKO, +46 90-786 52 96ST, +46 90-786 54 31Published 20.Dec.2021&nbsp;Last application date 15.Feb.2022 11:59 PM CET", "requirements_description": "N/A", "conditions_description": "N/A", "employer_description": "Ume\u00c3\u00a5 University was founded in 1965 and is Sweden's fifth oldest university. Today, we have a strong international and multicultural presence with students, teachers and researchers from all over the world.", "department_description": "N/A", "additional_information": "N/A", "apply_link": "N/A", "employer_link": "N/A", "job_type": "N/A", "logo": "https://content.academicpositions.com/eyJidWNrZXQiOiJhcC1wcm9kdWN0aW9uLW1lZGlhLWFyY2hpdmUiLCJrZXkiOiIyMDE2XC8wNFwvVW1lXHUwMGU1LnBuZyIsImVkaXRzIjpbXX0="}