{"url": "http://www.academictransfer.com/en/309328/universitair-docent-privaatrecht-in-het-bijzonder-het-goederenrecht-10-fte/apply/", "title": "Universitair docent Privaatrecht, in het bijzonder het goederenrecht (1,0 fte)", "publish_date": "2022-02-10", "deadline": "2022-03-13", "location": "Domplein 29, 3512 JE, Utrecht", "city": "Utrecht", "country": "Netherlands", "position": "Lecturer", "field": "Recht", "salary": "N/A", "max_working_hours": "36\u201440", "employer": "Utrecht University", "job_description": "Het Molengraaff Instituut voor Privaatrecht zoekt een universitair docent op het gebied van het privaatrecht, in het bijzonder het goederenrecht. Als UD doe je onderzoek en geef je onderwijs in samenwerking met de collega\u2019s binnen het instituut en het departement Rechtsgeleerdheid. Het onderwijs betreft zowel bachelor- als mastervakken, de begeleiding van scripties en het verrichten van co\u00f6rdinatie- en tutortaken. In eerste instantie is dertig procent van de werktijd gereserveerd voor onderzoek op jouw specialisatiegebied, waarbij je zoveel mogelijk aansluit bij \u00e9\u00e9n van de binnen het departement bestaande onderzoeksprogramma\u2019s. Een verdere uitbreiding van de onderzoekstijd behoort tot de mogelijkheden.", "requirements_description": "N/A", "conditions_description": "N/A", "employer_description": "N/A", "department_description": "N/A", "additional_information": "N/A", "apply_link": "N/A", "employer_link": "http://www.uu.nl/", "job_type": "TEMPORARY", "logo": "https://www.academictransfer.com/media/derivatives/logos/uu-en-wide/67674af2e9b77c72917924b654f37798.jpg"}