{"url": "https://www.funda.nl/koop/sprang-capelle/huis-88013394-dijkstraat-31/", "offer_type": "koop", "number_of_rooms": 8, "number_of_bathrooms": "N/A", "number_of_bedrooms": 6, "bathroom_facilities": "N/A", "number_of_floors": 3, "outdoor_space": "N/A", "facilities": "N/A", "volume_in_cubic_meters": 998, "living_area": 290, "plot_size": 1211, "external_storage_space": 23, "asking_price": 825000, "asking_price_per_square_meter": 2845, "rental_price": "N/A", "deposit": "N/A", "rental_agreement": "N/A", "language": "nl", "description": "<div class=\"object-description-body\" data-object-description-body=\"\" data-object-description-strip-markup=\"\">\r\nRUIME VRIJSTAANDE WONING  MET  GROTE MANTELZORGWONING  <br/>Met de  voordeur in Sprang-Capelle en  de  achterdeur grenzend aan Kaatsheuvel <br/> <br/>Onverwachts  opnieuw beschikbaar <br/> <br/>Deze woning ligt  op  de  grens van Kaatsheuvel  en Sprang-Capelle en bestaat uit 3 percelen, een ruime moderne vrijstaande hoofdwoning en een vrijstaande grote mantelzorgwoning. Geschikt dus voor dubbele bewoning en gelijkvloers wonen. <br/> <br/>Algemene kenmerken: <br/>* De voordeuren van zowel de hoofdwoning als de mantelzorgwoning liggen aan het eind van de doodlopende dijkstraat in Sprang Capelle <br/>* De elektrische schuifpoort bij de hoofdwoning ligt aan de Bevrijdingsweg te Kaatsheuvel <br/>* Ruimschoots parkeren op eigen grond mogelijk, ook voor aanhangers etc. <br/>* De schutting tussen de tuinen van de mantelzorgwoning en hoofdwoning bieden beide generaties privacy en nabijheid <br/>* Bij de hoofdwoning onder de speeltuin ligt een ge\u00efsoleerde betonvloer waar een garage geplaats mag worden indien er elders m2 bijgebouw wordt weggehaald <br/> <br/>De hoofdwoning kenmerkt zich o.a. door: <br/>* Zeer grote uitgebouwde leefkeuken (2019/2020) <br/>* Riante aangrenzende woonkamer <br/>* Vloerverwarming op de begane grond <br/>* Airco beneden verkoeld en (bij)verwarmt gehele beneden verdieping <br/>* Overal dubbel glas <br/>* Muur-, dak- en vloerisolatie <br/>* 3 slaapkamers op de 1ste verdieping <br/>* 1-2 slaapkamers op zolder <br/>* Badkamer met bad en douche <br/>* CV 2019 <br/> <br/>De gelijkvloerse mantelzorgwoning kenmerkt zich o.a. door: <br/>* Leefkeuken met openslaande tuindeuren <br/>* Woonkamer <br/>* Slaapkamer en douche/toilet beneden <br/>* Logeer/slaapkamer op de eerste verdieping <br/>* Privacy-biedende tuin met eigen vrijstaande duivenkooi/berging <br/>* Eigen CV 2017 <br/>* Tussenmeter <br/>* Ook geschikt (te maken) om te gebruiken als praktijk of kantoor aan huis <br/> <br/>De gemeente Waalwijk heeft op haar website actuele informatie staan over het beleid t.a.v. de voorwaarden voor (pre)mantelzorgwoningen. <br/> <br/>Deze woning met zijn mogelijkheden is uniek en, ondanks bovenstaande poging, met geen pen te beschrijven :-). Plan daarom snel een bezichtiging in. <br/> <br/>De informatie over deze woning is met grote zorg samengesteld. Ondanks alle zorgvuldigheid die we nastreven, kunnen aan deze informatie geen rechten worden ontleend. De plattegronden zijn indicatief en de genoemde maten zijn circa maten. Hier is om deze reden geen leveringsplicht aan verbonden. De informatie is uitsluitend bedoeld om een goede indruk van de woningen te geven\r\n    </div>", "image": "https://cloud.funda.nl/valentina_media/153/932/165_1440x960.jpg", "kind_of_house": "Eengezinswoning, vrijstaande woning", "construction_year": "N/A", "energy_label": "C ", "type_of_roof": "N/A", "heating": "N/A", "hot_water": "N/A", "boiler": "N/A", "location": "N/A", "garden": "Tuin rondom", "back_garden": "N/A", "garden_location": "N/A", "balcony": "N/A", "type_of_parking": "Op eigen terrein", "garage": "N/A", "zipcode": "5161 BW", "street": "Dijkstraat 31", "house_number": "31", "city": "sprangcapelle", "province": "noordbrabant", "lat": 51.6646, "lng": 5.038643, "offered_since": "N/A", "status": "beschikbaar", "object_type": "N/A", "type_of_apartment": "N/A", "type_of_construction": "Bestaande bouw", "business_space": "false", "neighborhood": "sprang", "in_the_neighborhood": "Basisschool Supermarkt Bushalte"}